{
  "command": "pamarith",
  "description": "Apply a binary function on two Netpbm images. See also: pamfunc. More information: https://netpbm.sourceforge.net/doc/pamarith.html.",
  "useCases": [
    {
      "description": "Apply the specified binary function pixel-wise on the two specified images (which must be of the same size):",
      "syntax": "pamarith -{{add|subtract|multiply|divide|difference|minimum|maximum|...}} {{path/to/image1.pam|pbm|pgm|ppm}} {{path/to/image2.pam|pbm|pgm|ppm}}"
    }
  ]
}